daug/__init__.py
daug/cogs/__init__.py
daug/cogs/authorization.py
daug/cogs/channels.py
daug/cogs/favorite.py
daug/cogs/join.py
daug/cogs/leave.py
daug/cogs/thread.py
daug/constants/__init__.py
daug/extensions/__init__.py
daug/utils/__init__.py
daug/utils/dpyexcept.py
daug/utils/dpylog.py
Daug-2023.12.9.1.dist-info/METADATA
Daug-2023.12.9.1.dist-info/WHEEL
Daug-2023.12.9.1.dist-info/top_level.txt
Daug-2023.12.9.1.dist-info/RECORD
